pyecharts_jupyter_installer/__init__.py
pyecharts_jupyter_installer/_version.py
pyecharts_jupyter_installer/jupyter_install.py
pyecharts_jupyter_installer-0.0.3.dist-info/DESCRIPTION.rst
pyecharts_jupyter_installer-0.0.3.dist-info/METADATA
pyecharts_jupyter_installer-0.0.3.dist-info/RECORD
pyecharts_jupyter_installer-0.0.3.dist-info/WHEEL
pyecharts_jupyter_installer-0.0.3.dist-info/metadata.json
pyecharts_jupyter_installer-0.0.3.dist-info/top_level.txt
